{"name":"ReflexDevTools","className":"Folder","filePaths":["default.project.json"],"children":[{"name":"app","className":"ModuleScript","filePaths":["out\\app.lua"]},{"name":"capture","className":"Script","filePaths":["out\\capture.server.lua"]},{"name":"plugin","className":"Script","filePaths":["out\\plugin.server.lua"]},{"name":"store","className":"ModuleScript","filePaths":["out\\store\\init.lua"],"children":[{"name":"game","className":"ModuleScript","filePaths":["out\\store\\game.lua"]},{"name":"widget","className":"ModuleScript","filePaths":["out\\store\\widget.lua"]}]},{"name":"vendor","className":"Folder","children":[{"name":"highlighter","className":"ModuleScript","filePaths":["out\\vendor\\highlighter\\init.lua"],"children":[{"name":"lexer","className":"ModuleScript","filePaths":["out\\vendor\\highlighter\\lexer\\init.lua"],"children":[{"name":"language","className":"ModuleScript","filePaths":["out\\vendor\\highlighter\\lexer\\language.lua"]}]},{"name":"theme","className":"ModuleScript","filePaths":["out\\vendor\\highlighter\\theme.lua"]},{"name":"types","className":"ModuleScript","filePaths":["out\\vendor\\highlighter\\types.lua"]},{"name":"utility","className":"ModuleScript","filePaths":["out\\vendor\\highlighter\\utility.lua"]}]}]},{"name":"include","className":"Folder","children":[{"name":"Promise","className":"ModuleScript","filePaths":["include\\Promise.lua"]},{"name":"RuntimeLib","className":"ModuleScript","filePaths":["include\\RuntimeLib.lua"]},{"name":"node_modules","className":"Folder","children":[{"name":"@rbxts","className":"Folder","children":[{"name":"compiler-types","className":"Folder","children":[{"name":"types","className":"Folder"}]},{"name":"inspect","className":"Folder","children":[{"name":"inspect","className":"ModuleScript","filePaths":["node_modules/@rbxts\\inspect\\inspect.lua"]}]},{"name":"LuauPolyfill","className":"ModuleScript","filePaths":["node_modules/@rbxts\\luau-polyfill-internal\\packages\\init.lua","node_modules/@rbxts\\luau-polyfill-internal\\default.project.json"],"children":[{"name":"Boolean","className":"ModuleScript","filePaths":["node_modules/@rbxts\\luau-polyfill-internal\\packages\\boolean\\src\\init.lua","node_modules/@rbxts\\luau-polyfill-internal\\packages\\boolean\\default.project.json"],"children":[{"name":"toJSBoolean","className":"ModuleScript","filePaths":["node_modules/@rbxts\\luau-polyfill-internal\\packages\\boolean\\src\\toJSBoolean.lua"]}]},{"name":"Collections","className":"ModuleScript","filePaths":["node_modules/@rbxts\\luau-polyfill-internal\\packages\\collections\\src\\init.lua","node_modules/@rbxts\\luau-polyfill-internal\\packages\\collections\\default.project.json"],"children":[{"name":"Array","className":"ModuleScript","filePaths":["node_modules/@rbxts\\luau-polyfill-internal\\packages\\collections\\src\\Array\\init.lua"],"children":[{"name":"concat","className":"ModuleScript","filePaths":["node_modules/@rbxts\\luau-polyfill-internal\\packages\\collections\\src\\Array\\concat.lua"]},{"name":"every","className":"ModuleScript","filePaths":["node_modules/@rbxts\\luau-polyfill-internal\\packages\\collections\\src\\Array\\every.lua"]},{"name":"filter","className":"ModuleScript","filePaths":["node_modules/@rbxts\\luau-polyfill-internal\\packages\\collections\\src\\Array\\filter.lua"]},{"name":"find","className":"ModuleScript","filePaths":["node_modules/@rbxts\\luau-polyfill-internal\\packages\\collections\\src\\Array\\find.lua"]},{"name":"findIndex","className":"ModuleScript","filePaths":["node_modules/@rbxts\\luau-polyfill-internal\\packages\\collections\\src\\Array\\findIndex.lua"]},{"name":"flat","className":"ModuleScript","filePaths":["node_modules/@rbxts\\luau-polyfill-internal\\packages\\collections\\src\\Array\\flat.lua"]},{"name":"flatMap","className":"ModuleScript","filePaths":["node_modules/@rbxts\\luau-polyfill-internal\\packages\\collections\\src\\Array\\flatMap.lua"]},{"name":"forEach","className":"ModuleScript","filePaths":["node_modules/@rbxts\\luau-polyfill-internal\\packages\\collections\\src\\Array\\forEach.lua"]},{"name":"from","className":"ModuleScript","filePaths":["node_modules/@rbxts\\luau-polyfill-internal\\packages\\collections\\src\\Array\\from\\init.lua"],"children":[{"name":"fromArray","className":"ModuleScript","filePaths":["node_modules/@rbxts\\luau-polyfill-internal\\packages\\collections\\src\\Array\\from\\fromArray.lua"]},{"name":"fromMap","className":"ModuleScript","filePaths":["node_modules/@rbxts\\luau-polyfill-internal\\packages\\collections\\src\\Array\\from\\fromMap.lua"]},{"name":"fromSet","className":"ModuleScript","filePaths":["node_modules/@rbxts\\luau-polyfill-internal\\packages\\collections\\src\\Array\\from\\fromSet.lua"]},{"name":"fromString","className":"ModuleScript","filePaths":["node_modules/@rbxts\\luau-polyfill-internal\\packages\\collections\\src\\Array\\from\\fromString.lua"]}]},{"name":"includes","className":"ModuleScript","filePaths":["node_modules/@rbxts\\luau-polyfill-internal\\packages\\collections\\src\\Array\\includes.lua"]},{"name":"indexOf","className":"ModuleScript","filePaths":["node_modules/@rbxts\\luau-polyfill-internal\\packages\\collections\\src\\Array\\indexOf.lua"]},{"name":"isArray","className":"ModuleScript","filePaths":["node_modules/@rbxts\\luau-polyfill-internal\\packages\\collections\\src\\Array\\isArray.lua"]},{"name":"join","className":"ModuleScript","filePaths":["node_modules/@rbxts\\luau-polyfill-internal\\packages\\collections\\src\\Array\\join.lua"]},{"name":"map","className":"ModuleScript","filePaths":["node_modules/@rbxts\\luau-polyfill-internal\\packages\\collections\\src\\Array\\map.lua"]},{"name":"reduce","className":"ModuleScript","filePaths":["node_modules/@rbxts\\luau-polyfill-internal\\packages\\collections\\src\\Array\\reduce.lua"]},{"name":"reverse","className":"ModuleScript","filePaths":["node_modules/@rbxts\\luau-polyfill-internal\\packages\\collections\\src\\Array\\reverse.lua"]},{"name":"shift","className":"ModuleScript","filePaths":["node_modules/@rbxts\\luau-polyfill-internal\\packages\\collections\\src\\Array\\shift.lua"]},{"name":"slice","className":"ModuleScript","filePaths":["node_modules/@rbxts\\luau-polyfill-internal\\packages\\collections\\src\\Array\\slice.lua"]},{"name":"some","className":"ModuleScript","filePaths":["node_modules/@rbxts\\luau-polyfill-internal\\packages\\collections\\src\\Array\\some.lua"]},{"name":"sort","className":"ModuleScript","filePaths":["node_modules/@rbxts\\luau-polyfill-internal\\packages\\collections\\src\\Array\\sort.lua"]},{"name":"splice","className":"ModuleScript","filePaths":["node_modules/@rbxts\\luau-polyfill-internal\\packages\\collections\\src\\Array\\splice.lua"]},{"name":"unshift","className":"ModuleScript","filePaths":["node_modules/@rbxts\\luau-polyfill-internal\\packages\\collections\\src\\Array\\unshift.lua"]}]},{"name":"Map","className":"ModuleScript","filePaths":["node_modules/@rbxts\\luau-polyfill-internal\\packages\\collections\\src\\Map\\init.lua"],"children":[{"name":"Map","className":"ModuleScript","filePaths":["node_modules/@rbxts\\luau-polyfill-internal\\packages\\collections\\src\\Map\\Map.lua"]},{"name":"coerceToMap","className":"ModuleScript","filePaths":["node_modules/@rbxts\\luau-polyfill-internal\\packages\\collections\\src\\Map\\coerceToMap.lua"]},{"name":"coerceToTable","className":"ModuleScript","filePaths":["node_modules/@rbxts\\luau-polyfill-internal\\packages\\collections\\src\\Map\\coerceToTable.lua"]}]},{"name":"Object","className":"ModuleScript","filePaths":["node_modules/@rbxts\\luau-polyfill-internal\\packages\\collections\\src\\Object\\init.lua"],"children":[{"name":"None","className":"ModuleScript","filePaths":["node_modules/@rbxts\\luau-polyfill-internal\\packages\\collections\\src\\Object\\None.lua"]},{"name":"assign","className":"ModuleScript","filePaths":["node_modules/@rbxts\\luau-polyfill-internal\\packages\\collections\\src\\Object\\assign.lua"]},{"name":"entries","className":"ModuleScript","filePaths":["node_modules/@rbxts\\luau-polyfill-internal\\packages\\collections\\src\\Object\\entries.lua"]},{"name":"freeze","className":"ModuleScript","filePaths":["node_modules/@rbxts\\luau-polyfill-internal\\packages\\collections\\src\\Object\\freeze.lua"]},{"name":"is","className":"ModuleScript","filePaths":["node_modules/@rbxts\\luau-polyfill-internal\\packages\\collections\\src\\Object\\is.lua"]},{"name":"isFrozen","className":"ModuleScript","filePaths":["node_modules/@rbxts\\luau-polyfill-internal\\packages\\collections\\src\\Object\\isFrozen.lua"]},{"name":"keys","className":"ModuleScript","filePaths":["node_modules/@rbxts\\luau-polyfill-internal\\packages\\collections\\src\\Object\\keys.lua"]},{"name":"preventExtensions","className":"ModuleScript","filePaths":["node_modules/@rbxts\\luau-polyfill-internal\\packages\\collections\\src\\Object\\preventExtensions.lua"]},{"name":"seal","className":"ModuleScript","filePaths":["node_modules/@rbxts\\luau-polyfill-internal\\packages\\collections\\src\\Object\\seal.lua"]},{"name":"values","className":"ModuleScript","filePaths":["node_modules/@rbxts\\luau-polyfill-internal\\packages\\collections\\src\\Object\\values.lua"]}]},{"name":"Set","className":"ModuleScript","filePaths":["node_modules/@rbxts\\luau-polyfill-internal\\packages\\collections\\src\\Set\\init.lua"]},{"name":"WeakMap","className":"ModuleScript","filePaths":["node_modules/@rbxts\\luau-polyfill-internal\\packages\\collections\\src\\WeakMap.lua"]},{"name":"inspect","className":"ModuleScript","filePaths":["node_modules/@rbxts\\luau-polyfill-internal\\packages\\collections\\src\\inspect.lua"]}]},{"name":"Console","className":"ModuleScript","filePaths":["node_modules/@rbxts\\luau-polyfill-internal\\packages\\console\\src\\init.lua","node_modules/@rbxts\\luau-polyfill-internal\\packages\\console\\default.project.json"],"children":[{"name":"makeConsoleImpl","className":"ModuleScript","filePaths":["node_modules/@rbxts\\luau-polyfill-internal\\packages\\console\\src\\makeConsoleImpl.lua"]}]},{"name":"ES7Types","className":"ModuleScript","filePaths":["node_modules/@rbxts\\luau-polyfill-internal\\packages\\es7-types\\src\\init.lua","node_modules/@rbxts\\luau-polyfill-internal\\packages\\es7-types\\default.project.json"]},{"name":"InstanceOf","className":"ModuleScript","filePaths":["node_modules/@rbxts\\luau-polyfill-internal\\packages\\instance-of\\src\\init.lua","node_modules/@rbxts\\luau-polyfill-internal\\packages\\instance-of\\default.project.json"],"children":[{"name":"instanceof","className":"ModuleScript","filePaths":["node_modules/@rbxts\\luau-polyfill-internal\\packages\\instance-of\\src\\instanceof.lua"]}]},{"name":"LuauPolyfill","className":"ModuleScript","filePaths":["node_modules/@rbxts\\luau-polyfill-internal\\packages\\luau-polyfill\\src\\init.lua","node_modules/@rbxts\\luau-polyfill-internal\\packages\\luau-polyfill\\default.project.json"],"children":[{"name":"AssertionError","className":"ModuleScript","filePaths":["node_modules/@rbxts\\luau-polyfill-internal\\packages\\luau-polyfill\\src\\AssertionError\\init.lua"],"children":[{"name":"AssertionError.global","className":"ModuleScript","filePaths":["node_modules/@rbxts\\luau-polyfill-internal\\packages\\luau-polyfill\\src\\AssertionError\\AssertionError.global.lua"]}]},{"name":"Error","className":"ModuleScript","filePaths":["node_modules/@rbxts\\luau-polyfill-internal\\packages\\luau-polyfill\\src\\Error\\init.lua"],"children":[{"name":"Error.global","className":"ModuleScript","filePaths":["node_modules/@rbxts\\luau-polyfill-internal\\packages\\luau-polyfill\\src\\Error\\Error.global.lua"]}]},{"name":"Promise","className":"ModuleScript","filePaths":["node_modules/@rbxts\\luau-polyfill-internal\\packages\\luau-polyfill\\src\\Promise.lua"]},{"name":"encodeURIComponent","className":"ModuleScript","filePaths":["node_modules/@rbxts\\luau-polyfill-internal\\packages\\luau-polyfill\\src\\encodeURIComponent.lua"]},{"name":"extends","className":"ModuleScript","filePaths":["node_modules/@rbxts\\luau-polyfill-internal\\packages\\luau-polyfill\\src\\extends.lua"]}]},{"name":"Math","className":"ModuleScript","filePaths":["node_modules/@rbxts\\luau-polyfill-internal\\packages\\math\\src\\init.lua","node_modules/@rbxts\\luau-polyfill-internal\\packages\\math\\default.project.json"]},{"name":"Number","className":"ModuleScript","filePaths":["node_modules/@rbxts\\luau-polyfill-internal\\packages\\number\\src\\init.lua","node_modules/@rbxts\\luau-polyfill-internal\\packages\\number\\default.project.json"],"children":[{"name":"MAX_SAFE_INTEGER","className":"ModuleScript","filePaths":["node_modules/@rbxts\\luau-polyfill-internal\\packages\\number\\src\\MAX_SAFE_INTEGER.lua"]},{"name":"MIN_SAFE_INTEGER","className":"ModuleScript","filePaths":["node_modules/@rbxts\\luau-polyfill-internal\\packages\\number\\src\\MIN_SAFE_INTEGER.lua"]},{"name":"isFinite","className":"ModuleScript","filePaths":["node_modules/@rbxts\\luau-polyfill-internal\\packages\\number\\src\\isFinite.lua"]},{"name":"isInteger","className":"ModuleScript","filePaths":["node_modules/@rbxts\\luau-polyfill-internal\\packages\\number\\src\\isInteger.lua"]},{"name":"isNaN","className":"ModuleScript","filePaths":["node_modules/@rbxts\\luau-polyfill-internal\\packages\\number\\src\\isNaN.lua"]},{"name":"isSafeInteger","className":"ModuleScript","filePaths":["node_modules/@rbxts\\luau-polyfill-internal\\packages\\number\\src\\isSafeInteger.lua"]},{"name":"toExponential","className":"ModuleScript","filePaths":["node_modules/@rbxts\\luau-polyfill-internal\\packages\\number\\src\\toExponential.lua"]}]},{"name":"String","className":"ModuleScript","filePaths":["node_modules/@rbxts\\luau-polyfill-internal\\packages\\string\\src\\init.lua","node_modules/@rbxts\\luau-polyfill-internal\\packages\\string\\default.project.json"],"children":[{"name":"charCodeAt","className":"ModuleScript","filePaths":["node_modules/@rbxts\\luau-polyfill-internal\\packages\\string\\src\\charCodeAt.lua"]},{"name":"endsWith","className":"ModuleScript","filePaths":["node_modules/@rbxts\\luau-polyfill-internal\\packages\\string\\src\\endsWith.lua"]},{"name":"findOr","className":"ModuleScript","filePaths":["node_modules/@rbxts\\luau-polyfill-internal\\packages\\string\\src\\findOr.lua"]},{"name":"includes","className":"ModuleScript","filePaths":["node_modules/@rbxts\\luau-polyfill-internal\\packages\\string\\src\\includes.lua"]},{"name":"indexOf","className":"ModuleScript","filePaths":["node_modules/@rbxts\\luau-polyfill-internal\\packages\\string\\src\\indexOf.lua"]},{"name":"lastIndexOf","className":"ModuleScript","filePaths":["node_modules/@rbxts\\luau-polyfill-internal\\packages\\string\\src\\lastIndexOf.lua"]},{"name":"slice","className":"ModuleScript","filePaths":["node_modules/@rbxts\\luau-polyfill-internal\\packages\\string\\src\\slice.lua"]},{"name":"split","className":"ModuleScript","filePaths":["node_modules/@rbxts\\luau-polyfill-internal\\packages\\string\\src\\split.lua"]},{"name":"startsWith","className":"ModuleScript","filePaths":["node_modules/@rbxts\\luau-polyfill-internal\\packages\\string\\src\\startsWith.lua"]},{"name":"substr","className":"ModuleScript","filePaths":["node_modules/@rbxts\\luau-polyfill-internal\\packages\\string\\src\\substr.lua"]},{"name":"trim","className":"ModuleScript","filePaths":["node_modules/@rbxts\\luau-polyfill-internal\\packages\\string\\src\\trim.lua"]},{"name":"trimEnd","className":"ModuleScript","filePaths":["node_modules/@rbxts\\luau-polyfill-internal\\packages\\string\\src\\trimEnd.lua"]},{"name":"trimStart","className":"ModuleScript","filePaths":["node_modules/@rbxts\\luau-polyfill-internal\\packages\\string\\src\\trimStart.lua"]}]},{"name":"Symbol","className":"ModuleScript","filePaths":["node_modules/@rbxts\\luau-polyfill-internal\\packages\\symbol\\src\\init.lua","node_modules/@rbxts\\luau-polyfill-internal\\packages\\symbol\\default.project.json"],"children":[{"name":"GlobalRegistry","className":"ModuleScript","filePaths":["node_modules/@rbxts\\luau-polyfill-internal\\packages\\symbol\\src\\GlobalRegistry.lua"]},{"name":"Registry.global","className":"ModuleScript","filePaths":["node_modules/@rbxts\\luau-polyfill-internal\\packages\\symbol\\src\\Registry.global.lua"]},{"name":"Symbol","className":"ModuleScript","filePaths":["node_modules/@rbxts\\luau-polyfill-internal\\packages\\symbol\\src\\Symbol.lua"]}]},{"name":"Timers","className":"ModuleScript","filePaths":["node_modules/@rbxts\\luau-polyfill-internal\\packages\\timers\\src\\init.lua","node_modules/@rbxts\\luau-polyfill-internal\\packages\\timers\\default.project.json"],"children":[{"name":"makeIntervalImpl","className":"ModuleScript","filePaths":["node_modules/@rbxts\\luau-polyfill-internal\\packages\\timers\\src\\makeIntervalImpl.lua"]},{"name":"makeTimerImpl","className":"ModuleScript","filePaths":["node_modules/@rbxts\\luau-polyfill-internal\\packages\\timers\\src\\makeTimerImpl.lua"]}]}]},{"name":"Promise","className":"ModuleScript","filePaths":["node_modules/@rbxts\\promise-forward\\src\\init.lua","node_modules/@rbxts\\promise-forward\\default.project.json"]},{"name":"React","className":"ModuleScript","filePaths":["node_modules/@rbxts\\react-internal\\src\\init.luau","node_modules/@rbxts\\react-internal\\default.project.json"],"children":[{"name":"None.roblox","className":"ModuleScript","filePaths":["node_modules/@rbxts\\react-internal\\src\\None.roblox.luau"]},{"name":"React","className":"ModuleScript","filePaths":["node_modules/@rbxts\\react-internal\\src\\React.luau"]},{"name":"ReactBaseClasses","className":"ModuleScript","filePaths":["node_modules/@rbxts\\react-internal\\src\\ReactBaseClasses.luau"]},{"name":"ReactBinding.roblox","className":"ModuleScript","filePaths":["node_modules/@rbxts\\react-internal\\src\\ReactBinding.roblox.luau"]},{"name":"ReactChildren","className":"ModuleScript","filePaths":["node_modules/@rbxts\\react-internal\\src\\ReactChildren.luau"]},{"name":"ReactContext","className":"ModuleScript","filePaths":["node_modules/@rbxts\\react-internal\\src\\ReactContext.luau"]},{"name":"ReactCreateRef","className":"ModuleScript","filePaths":["node_modules/@rbxts\\react-internal\\src\\ReactCreateRef.luau"]},{"name":"ReactElement","className":"ModuleScript","filePaths":["node_modules/@rbxts\\react-internal\\src\\ReactElement.luau"]},{"name":"ReactElementValidator","className":"ModuleScript","filePaths":["node_modules/@rbxts\\react-internal\\src\\ReactElementValidator.luau"]},{"name":"ReactForwardRef","className":"ModuleScript","filePaths":["node_modules/@rbxts\\react-internal\\src\\ReactForwardRef.luau"]},{"name":"ReactHooks","className":"ModuleScript","filePaths":["node_modules/@rbxts\\react-internal\\src\\ReactHooks.luau"]},{"name":"ReactLazy","className":"ModuleScript","filePaths":["node_modules/@rbxts\\react-internal\\src\\ReactLazy.luau"]},{"name":"ReactMemo","className":"ModuleScript","filePaths":["node_modules/@rbxts\\react-internal\\src\\ReactMemo.luau"]},{"name":"ReactMutableSource","className":"ModuleScript","filePaths":["node_modules/@rbxts\\react-internal\\src\\ReactMutableSource.luau"]},{"name":"ReactNoopUpdateQueue","className":"ModuleScript","filePaths":["node_modules/@rbxts\\react-internal\\src\\ReactNoopUpdateQueue.luau"]},{"name":"createSignal.roblox","className":"ModuleScript","filePaths":["node_modules/@rbxts\\react-internal\\src\\createSignal.roblox.luau"]}]},{"name":"ReactReconciler","className":"ModuleScript","filePaths":["node_modules/@rbxts\\react-reconciler-internal\\src\\init.luau","node_modules/@rbxts\\react-reconciler-internal\\default.project.json"],"children":[{"name":"DebugTracing","className":"ModuleScript","filePaths":["node_modules/@rbxts\\react-reconciler-internal\\src\\DebugTracing.luau"]},{"name":"MaxInts","className":"ModuleScript","filePaths":["node_modules/@rbxts\\react-reconciler-internal\\src\\MaxInts.luau"]},{"name":"ReactCapturedValue","className":"ModuleScript","filePaths":["node_modules/@rbxts\\react-reconciler-internal\\src\\ReactCapturedValue.luau"]},{"name":"ReactChildFiber.new","className":"ModuleScript","filePaths":["node_modules/@rbxts\\react-reconciler-internal\\src\\ReactChildFiber.new.luau"]},{"name":"ReactCurrentFiber","className":"ModuleScript","filePaths":["node_modules/@rbxts\\react-reconciler-internal\\src\\ReactCurrentFiber.luau"]},{"name":"ReactFiber.new","className":"ModuleScript","filePaths":["node_modules/@rbxts\\react-reconciler-internal\\src\\ReactFiber.new.luau"]},{"name":"ReactFiberBeginWork.new","className":"ModuleScript","filePaths":["node_modules/@rbxts\\react-reconciler-internal\\src\\ReactFiberBeginWork.new.luau"]},{"name":"ReactFiberClassComponent.new","className":"ModuleScript","filePaths":["node_modules/@rbxts\\react-reconciler-internal\\src\\ReactFiberClassComponent.new.luau"]},{"name":"ReactFiberCommitWork.new","className":"ModuleScript","filePaths":["node_modules/@rbxts\\react-reconciler-internal\\src\\ReactFiberCommitWork.new.luau"]},{"name":"ReactFiberCompleteWork.new","className":"ModuleScript","filePaths":["node_modules/@rbxts\\react-reconciler-internal\\src\\ReactFiberCompleteWork.new.luau"]},{"name":"ReactFiberComponentStack","className":"ModuleScript","filePaths":["node_modules/@rbxts\\react-reconciler-internal\\src\\ReactFiberComponentStack.luau"]},{"name":"ReactFiberContext.new","className":"ModuleScript","filePaths":["node_modules/@rbxts\\react-reconciler-internal\\src\\ReactFiberContext.new.luau"]},{"name":"ReactFiberDevToolsHook.new","className":"ModuleScript","filePaths":["node_modules/@rbxts\\react-reconciler-internal\\src\\ReactFiberDevToolsHook.new.luau"]},{"name":"ReactFiberErrorDialog","className":"ModuleScript","filePaths":["node_modules/@rbxts\\react-reconciler-internal\\src\\ReactFiberErrorDialog.luau"]},{"name":"ReactFiberErrorLogger","className":"ModuleScript","filePaths":["node_modules/@rbxts\\react-reconciler-internal\\src\\ReactFiberErrorLogger.luau"]},{"name":"ReactFiberFlags","className":"ModuleScript","filePaths":["node_modules/@rbxts\\react-reconciler-internal\\src\\ReactFiberFlags.luau"]},{"name":"ReactFiberHooks.new","className":"ModuleScript","filePaths":["node_modules/@rbxts\\react-reconciler-internal\\src\\ReactFiberHooks.new.luau"]},{"name":"ReactFiberHostConfig","className":"ModuleScript","filePaths":["node_modules/@rbxts\\react-reconciler-internal\\src\\ReactFiberHostConfig.luau"]},{"name":"ReactFiberHostContext.new","className":"ModuleScript","filePaths":["node_modules/@rbxts\\react-reconciler-internal\\src\\ReactFiberHostContext.new.luau"]},{"name":"ReactFiberHotReloading.new","className":"ModuleScript","filePaths":["node_modules/@rbxts\\react-reconciler-internal\\src\\ReactFiberHotReloading.new.luau"]},{"name":"ReactFiberHydrationContext.new","className":"ModuleScript","filePaths":["node_modules/@rbxts\\react-reconciler-internal\\src\\ReactFiberHydrationContext.new.luau"]},{"name":"ReactFiberLane","className":"ModuleScript","filePaths":["node_modules/@rbxts\\react-reconciler-internal\\src\\ReactFiberLane.luau"]},{"name":"ReactFiberLazyComponent.new","className":"ModuleScript","filePaths":["node_modules/@rbxts\\react-reconciler-internal\\src\\ReactFiberLazyComponent.new.luau"]},{"name":"ReactFiberNewContext.new","className":"ModuleScript","filePaths":["node_modules/@rbxts\\react-reconciler-internal\\src\\ReactFiberNewContext.new.luau"]},{"name":"ReactFiberOffscreenComponent","className":"ModuleScript","filePaths":["node_modules/@rbxts\\react-reconciler-internal\\src\\ReactFiberOffscreenComponent.luau"]},{"name":"ReactFiberReconciler","className":"ModuleScript","filePaths":["node_modules/@rbxts\\react-reconciler-internal\\src\\ReactFiberReconciler.luau"]},{"name":"ReactFiberReconciler.new","className":"ModuleScript","filePaths":["node_modules/@rbxts\\react-reconciler-internal\\src\\ReactFiberReconciler.new.luau"]},{"name":"ReactFiberRoot.new","className":"ModuleScript","filePaths":["node_modules/@rbxts\\react-reconciler-internal\\src\\ReactFiberRoot.new.luau"]},{"name":"ReactFiberSchedulerPriorities.roblox","className":"ModuleScript","filePaths":["node_modules/@rbxts\\react-reconciler-internal\\src\\ReactFiberSchedulerPriorities.roblox.luau"]},{"name":"ReactFiberStack.new","className":"ModuleScript","filePaths":["node_modules/@rbxts\\react-reconciler-internal\\src\\ReactFiberStack.new.luau"]},{"name":"ReactFiberSuspenseComponent.new","className":"ModuleScript","filePaths":["node_modules/@rbxts\\react-reconciler-internal\\src\\ReactFiberSuspenseComponent.new.luau"]},{"name":"ReactFiberSuspenseContext.new","className":"ModuleScript","filePaths":["node_modules/@rbxts\\react-reconciler-internal\\src\\ReactFiberSuspenseContext.new.luau"]},{"name":"ReactFiberThrow.new","className":"ModuleScript","filePaths":["node_modules/@rbxts\\react-reconciler-internal\\src\\ReactFiberThrow.new.luau"]},{"name":"ReactFiberTransition","className":"ModuleScript","filePaths":["node_modules/@rbxts\\react-reconciler-internal\\src\\ReactFiberTransition.luau"]},{"name":"ReactFiberTreeReflection","className":"ModuleScript","filePaths":["node_modules/@rbxts\\react-reconciler-internal\\src\\ReactFiberTreeReflection.luau"]},{"name":"ReactFiberUnwindWork.new","className":"ModuleScript","filePaths":["node_modules/@rbxts\\react-reconciler-internal\\src\\ReactFiberUnwindWork.new.luau"]},{"name":"ReactFiberWorkInProgress","className":"ModuleScript","filePaths":["node_modules/@rbxts\\react-reconciler-internal\\src\\ReactFiberWorkInProgress.luau"]},{"name":"ReactFiberWorkLoop.new","className":"ModuleScript","filePaths":["node_modules/@rbxts\\react-reconciler-internal\\src\\ReactFiberWorkLoop.new.luau"]},{"name":"ReactHookEffectTags","className":"ModuleScript","filePaths":["node_modules/@rbxts\\react-reconciler-internal\\src\\ReactHookEffectTags.luau"]},{"name":"ReactInternalTypes","className":"ModuleScript","filePaths":["node_modules/@rbxts\\react-reconciler-internal\\src\\ReactInternalTypes.luau"]},{"name":"ReactMutableSource.new","className":"ModuleScript","filePaths":["node_modules/@rbxts\\react-reconciler-internal\\src\\ReactMutableSource.new.luau"]},{"name":"ReactPortal","className":"ModuleScript","filePaths":["node_modules/@rbxts\\react-reconciler-internal\\src\\ReactPortal.luau"]},{"name":"ReactProfilerTimer.new","className":"ModuleScript","filePaths":["node_modules/@rbxts\\react-reconciler-internal\\src\\ReactProfilerTimer.new.luau"]},{"name":"ReactRootTags","className":"ModuleScript","filePaths":["node_modules/@rbxts\\react-reconciler-internal\\src\\ReactRootTags.luau"]},{"name":"ReactStrictModeWarnings.new","className":"ModuleScript","filePaths":["node_modules/@rbxts\\react-reconciler-internal\\src\\ReactStrictModeWarnings.new.luau"]},{"name":"ReactTestSelectors","className":"ModuleScript","filePaths":["node_modules/@rbxts\\react-reconciler-internal\\src\\ReactTestSelectors.luau"]},{"name":"ReactTypeOfMode","className":"ModuleScript","filePaths":["node_modules/@rbxts\\react-reconciler-internal\\src\\ReactTypeOfMode.luau"]},{"name":"ReactUpdateQueue.new","className":"ModuleScript","filePaths":["node_modules/@rbxts\\react-reconciler-internal\\src\\ReactUpdateQueue.new.luau"]},{"name":"ReactWorkTags","className":"ModuleScript","filePaths":["node_modules/@rbxts\\react-reconciler-internal\\src\\ReactWorkTags.luau"]},{"name":"SchedulerWithReactIntegration.new","className":"ModuleScript","filePaths":["node_modules/@rbxts\\react-reconciler-internal\\src\\SchedulerWithReactIntegration.new.luau"]},{"name":"SchedulingProfiler","className":"ModuleScript","filePaths":["node_modules/@rbxts\\react-reconciler-internal\\src\\SchedulingProfiler.luau"]},{"name":"forks","className":"Folder","children":[{"name":"ReactFiberHostConfig.test","className":"ModuleScript","filePaths":["node_modules/@rbxts\\react-reconciler-internal\\src\\forks\\ReactFiberHostConfig.test.luau"]}]}]},{"name":"react-reflex","className":"ModuleScript","filePaths":["node_modules/@rbxts\\react-reflex\\out\\init.lua","node_modules/@rbxts\\react-reflex\\default.project.json"],"children":[{"name":"components","className":"Folder","children":[{"name":"ReflexContext","className":"ModuleScript","filePaths":["node_modules/@rbxts\\react-reflex\\out\\components\\ReflexContext.lua"]},{"name":"ReflexProvider","className":"ModuleScript","filePaths":["node_modules/@rbxts\\react-reflex\\out\\components\\ReflexProvider.lua"]}]},{"name":"hooks","className":"Folder","children":[{"name":"use-producer","className":"ModuleScript","filePaths":["node_modules/@rbxts\\react-reflex\\out\\hooks\\use-producer.lua"]},{"name":"use-selector-creator","className":"ModuleScript","filePaths":["node_modules/@rbxts\\react-reflex\\out\\hooks\\use-selector-creator.lua"]},{"name":"use-selector","className":"ModuleScript","filePaths":["node_modules/@rbxts\\react-reflex\\out\\hooks\\use-selector.lua"]}]}]},{"name":"ReactRoblox","className":"ModuleScript","filePaths":["node_modules/@rbxts\\react-roblox\\src\\init.luau","node_modules/@rbxts\\react-roblox\\default.project.json"],"children":[{"name":"ReactReconciler.roblox","className":"ModuleScript","filePaths":["node_modules/@rbxts\\react-roblox\\src\\ReactReconciler.roblox.luau"]},{"name":"client","className":"Folder","children":[{"name":"ReactRoblox","className":"ModuleScript","filePaths":["node_modules/@rbxts\\react-roblox\\src\\client\\ReactRoblox.luau"]},{"name":"ReactRobloxComponent","className":"ModuleScript","filePaths":["node_modules/@rbxts\\react-roblox\\src\\client\\ReactRobloxComponent.luau"]},{"name":"ReactRobloxComponentTree","className":"ModuleScript","filePaths":["node_modules/@rbxts\\react-roblox\\src\\client\\ReactRobloxComponentTree.luau"]},{"name":"ReactRobloxHostConfig","className":"ModuleScript","filePaths":["node_modules/@rbxts\\react-roblox\\src\\client\\ReactRobloxHostConfig.luau"]},{"name":"ReactRobloxHostTypes.roblox","className":"ModuleScript","filePaths":["node_modules/@rbxts\\react-roblox\\src\\client\\ReactRobloxHostTypes.roblox.luau"]},{"name":"ReactRobloxRoot","className":"ModuleScript","filePaths":["node_modules/@rbxts\\react-roblox\\src\\client\\ReactRobloxRoot.luau"]},{"name":"roblox","className":"Folder","children":[{"name":"RobloxComponentProps","className":"ModuleScript","filePaths":["node_modules/@rbxts\\react-roblox\\src\\client\\roblox\\RobloxComponentProps.luau"]},{"name":"SingleEventManager","className":"ModuleScript","filePaths":["node_modules/@rbxts\\react-roblox\\src\\client\\roblox\\SingleEventManager.luau"]},{"name":"getDefaultInstanceProperty","className":"ModuleScript","filePaths":["node_modules/@rbxts\\react-roblox\\src\\client\\roblox\\getDefaultInstanceProperty.luau"]}]}]}]},{"name":"RoactTS","className":"ModuleScript","filePaths":["node_modules/@rbxts\\react-ts\\src\\init.lua","node_modules/@rbxts\\react-ts\\default.project.json"],"children":[{"name":"types","className":"Folder"}]},{"name":"reflex","className":"Folder","children":[{"name":"src","className":"ModuleScript","filePaths":["node_modules/@rbxts\\reflex\\src\\init.lua"],"children":[{"name":"Promise","className":"ModuleScript","filePaths":["node_modules/@rbxts\\reflex\\src\\Promise.lua"]},{"name":"applyMiddleware","className":"ModuleScript","filePaths":["node_modules/@rbxts\\reflex\\src\\applyMiddleware.lua"]},{"name":"broadcast","className":"ModuleScript","filePaths":["node_modules/@rbxts\\reflex\\src\\broadcast\\init.lua"],"children":[{"name":"createBroadcastReceiver","className":"ModuleScript","filePaths":["node_modules/@rbxts\\reflex\\src\\broadcast\\createBroadcastReceiver.lua"]},{"name":"createBroadcaster","className":"ModuleScript","filePaths":["node_modules/@rbxts\\reflex\\src\\broadcast\\createBroadcaster.lua"]},{"name":"hydrate","className":"ModuleScript","filePaths":["node_modules/@rbxts\\reflex\\src\\broadcast\\hydrate.lua"]}]},{"name":"combineProducers","className":"ModuleScript","filePaths":["node_modules/@rbxts\\reflex\\src\\combineProducers.lua"]},{"name":"createProducer","className":"ModuleScript","filePaths":["node_modules/@rbxts\\reflex\\src\\createProducer.lua"]},{"name":"createSelector","className":"ModuleScript","filePaths":["node_modules/@rbxts\\reflex\\src\\createSelector.lua"]},{"name":"middleware","className":"Folder","children":[{"name":"loggerMiddleware","className":"ModuleScript","filePaths":["node_modules/@rbxts\\reflex\\src\\middleware\\loggerMiddleware.lua"]}]},{"name":"types","className":"ModuleScript","filePaths":["node_modules/@rbxts\\reflex\\src\\types.lua"]},{"name":"utils","className":"Folder","children":[{"name":"createSelectArrayDiffs","className":"ModuleScript","filePaths":["node_modules/@rbxts\\reflex\\src\\utils\\createSelectArrayDiffs.lua"]},{"name":"setInterval","className":"ModuleScript","filePaths":["node_modules/@rbxts\\reflex\\src\\utils\\setInterval.lua"]},{"name":"shallowEqual","className":"ModuleScript","filePaths":["node_modules/@rbxts\\reflex\\src\\utils\\shallowEqual.lua"]},{"name":"testSelector","className":"ModuleScript","filePaths":["node_modules/@rbxts\\reflex\\src\\utils\\testSelector.lua"]}]}]}]},{"name":"RoactTS","className":"ModuleScript","filePaths":["node_modules/@rbxts\\roact\\src\\init.lua","node_modules/@rbxts\\roact\\default.project.json"],"children":[{"name":"types","className":"Folder"}]},{"name":"RoactCompat","className":"ModuleScript","filePaths":["node_modules/@rbxts\\roact-compat-internal\\src\\init.luau","node_modules/@rbxts\\roact-compat-internal\\default.project.json"],"children":[{"name":"Portal","className":"ModuleScript","filePaths":["node_modules/@rbxts\\roact-compat-internal\\src\\Portal.luau"]},{"name":"RoactTree","className":"ModuleScript","filePaths":["node_modules/@rbxts\\roact-compat-internal\\src\\RoactTree.luau"]},{"name":"createFragment","className":"ModuleScript","filePaths":["node_modules/@rbxts\\roact-compat-internal\\src\\createFragment.luau"]},{"name":"oneChild","className":"ModuleScript","filePaths":["node_modules/@rbxts\\roact-compat-internal\\src\\oneChild.luau"]},{"name":"setGlobalConfig","className":"ModuleScript","filePaths":["node_modules/@rbxts\\roact-compat-internal\\src\\setGlobalConfig.luau"]},{"name":"warnOnce","className":"ModuleScript","filePaths":["node_modules/@rbxts\\roact-compat-internal\\src\\warnOnce.luau"]}]},{"name":"Scheduler","className":"ModuleScript","filePaths":["node_modules/@rbxts\\scheduler-internal\\src\\init.luau","node_modules/@rbxts\\scheduler-internal\\default.project.json"],"children":[{"name":"Scheduler","className":"ModuleScript","filePaths":["node_modules/@rbxts\\scheduler-internal\\src\\Scheduler.luau"]},{"name":"SchedulerFeatureFlags","className":"ModuleScript","filePaths":["node_modules/@rbxts\\scheduler-internal\\src\\SchedulerFeatureFlags.luau"]},{"name":"SchedulerHostConfig","className":"ModuleScript","filePaths":["node_modules/@rbxts\\scheduler-internal\\src\\SchedulerHostConfig.luau"]},{"name":"SchedulerMinHeap","className":"ModuleScript","filePaths":["node_modules/@rbxts\\scheduler-internal\\src\\SchedulerMinHeap.luau"]},{"name":"SchedulerPriorities","className":"ModuleScript","filePaths":["node_modules/@rbxts\\scheduler-internal\\src\\SchedulerPriorities.luau"]},{"name":"SchedulerProfiling","className":"ModuleScript","filePaths":["node_modules/@rbxts\\scheduler-internal\\src\\SchedulerProfiling.luau"]},{"name":"Tracing","className":"ModuleScript","filePaths":["node_modules/@rbxts\\scheduler-internal\\src\\Tracing.luau"]},{"name":"TracingSubscriptions","className":"ModuleScript","filePaths":["node_modules/@rbxts\\scheduler-internal\\src\\TracingSubscriptions.luau"]},{"name":"forks","className":"Folder","children":[{"name":"SchedulerHostConfig.default","className":"ModuleScript","filePaths":["node_modules/@rbxts\\scheduler-internal\\src\\forks\\SchedulerHostConfig.default.luau"]},{"name":"SchedulerHostConfig.mock","className":"ModuleScript","filePaths":["node_modules/@rbxts\\scheduler-internal\\src\\forks\\SchedulerHostConfig.mock.luau"]}]},{"name":"unstable_mock","className":"ModuleScript","filePaths":["node_modules/@rbxts\\scheduler-internal\\src\\unstable_mock.luau"]}]},{"name":"services","className":"ModuleScript","filePaths":["node_modules/@rbxts\\services\\init.lua"]},{"name":"Shared","className":"ModuleScript","filePaths":["node_modules/@rbxts\\shared-internal\\src\\init.luau","node_modules/@rbxts\\shared-internal\\default.project.json"],"children":[{"name":"ConsolePatchingDev.roblox","className":"ModuleScript","filePaths":["node_modules/@rbxts\\shared-internal\\src\\ConsolePatchingDev.roblox.luau"]},{"name":"ErrorHandling.roblox","className":"ModuleScript","filePaths":["node_modules/@rbxts\\shared-internal\\src\\ErrorHandling.roblox.luau"]},{"name":"ExecutionEnvironment","className":"ModuleScript","filePaths":["node_modules/@rbxts\\shared-internal\\src\\ExecutionEnvironment.luau"]},{"name":"PropMarkers","className":"Folder","children":[{"name":"Change","className":"ModuleScript","filePaths":["node_modules/@rbxts\\shared-internal\\src\\PropMarkers\\Change.luau"]},{"name":"Event","className":"ModuleScript","filePaths":["node_modules/@rbxts\\shared-internal\\src\\PropMarkers\\Event.luau"]},{"name":"Tag","className":"ModuleScript","filePaths":["node_modules/@rbxts\\shared-internal\\src\\PropMarkers\\Tag.luau"]}]},{"name":"ReactComponentStackFrame","className":"ModuleScript","filePaths":["node_modules/@rbxts\\shared-internal\\src\\ReactComponentStackFrame.luau"]},{"name":"ReactElementType","className":"ModuleScript","filePaths":["node_modules/@rbxts\\shared-internal\\src\\ReactElementType.luau"]},{"name":"ReactErrorUtils","className":"ModuleScript","filePaths":["node_modules/@rbxts\\shared-internal\\src\\ReactErrorUtils.luau"]},{"name":"ReactFeatureFlags","className":"ModuleScript","filePaths":["node_modules/@rbxts\\shared-internal\\src\\ReactFeatureFlags.luau"]},{"name":"ReactFiberHostConfig","className":"ModuleScript","filePaths":["node_modules/@rbxts\\shared-internal\\src\\ReactFiberHostConfig\\init.luau"],"children":[{"name":"WithNoHydration","className":"ModuleScript","filePaths":["node_modules/@rbxts\\shared-internal\\src\\ReactFiberHostConfig\\WithNoHydration.luau"]},{"name":"WithNoPersistence","className":"ModuleScript","filePaths":["node_modules/@rbxts\\shared-internal\\src\\ReactFiberHostConfig\\WithNoPersistence.luau"]},{"name":"WithNoTestSelectors","className":"ModuleScript","filePaths":["node_modules/@rbxts\\shared-internal\\src\\ReactFiberHostConfig\\WithNoTestSelectors.luau"]}]},{"name":"ReactInstanceMap","className":"ModuleScript","filePaths":["node_modules/@rbxts\\shared-internal\\src\\ReactInstanceMap.luau"]},{"name":"ReactSharedInternals","className":"ModuleScript","filePaths":["node_modules/@rbxts\\shared-internal\\src\\ReactSharedInternals\\init.luau"],"children":[{"name":"IsSomeRendererActing","className":"ModuleScript","filePaths":["node_modules/@rbxts\\shared-internal\\src\\ReactSharedInternals\\IsSomeRendererActing.luau"]},{"name":"ReactCurrentBatchConfig","className":"ModuleScript","filePaths":["node_modules/@rbxts\\shared-internal\\src\\ReactSharedInternals\\ReactCurrentBatchConfig.luau"]},{"name":"ReactCurrentDispatcher","className":"ModuleScript","filePaths":["node_modules/@rbxts\\shared-internal\\src\\ReactSharedInternals\\ReactCurrentDispatcher.luau"]},{"name":"ReactCurrentOwner","className":"ModuleScript","filePaths":["node_modules/@rbxts\\shared-internal\\src\\ReactSharedInternals\\ReactCurrentOwner.luau"]},{"name":"ReactDebugCurrentFrame","className":"ModuleScript","filePaths":["node_modules/@rbxts\\shared-internal\\src\\ReactSharedInternals\\ReactDebugCurrentFrame.luau"]}]},{"name":"ReactSymbols","className":"ModuleScript","filePaths":["node_modules/@rbxts\\shared-internal\\src\\ReactSymbols.luau"]},{"name":"ReactTypes","className":"ModuleScript","filePaths":["node_modules/@rbxts\\shared-internal\\src\\ReactTypes.luau"]},{"name":"ReactVersion","className":"ModuleScript","filePaths":["node_modules/@rbxts\\shared-internal\\src\\ReactVersion.luau"]},{"name":"Symbol.roblox","className":"ModuleScript","filePaths":["node_modules/@rbxts\\shared-internal\\src\\Symbol.roblox.luau"]},{"name":"Type.roblox","className":"ModuleScript","filePaths":["node_modules/@rbxts\\shared-internal\\src\\Type.roblox.luau"]},{"name":"UninitializedState.roblox","className":"ModuleScript","filePaths":["node_modules/@rbxts\\shared-internal\\src\\UninitializedState.roblox.luau"]},{"name":"checkPropTypes","className":"ModuleScript","filePaths":["node_modules/@rbxts\\shared-internal\\src\\checkPropTypes.luau"]},{"name":"console","className":"ModuleScript","filePaths":["node_modules/@rbxts\\shared-internal\\src\\console.luau"]},{"name":"consoleWithStackDev","className":"ModuleScript","filePaths":["node_modules/@rbxts\\shared-internal\\src\\consoleWithStackDev.luau"]},{"name":"enqueueTask.roblox","className":"ModuleScript","filePaths":["node_modules/@rbxts\\shared-internal\\src\\enqueueTask.roblox.luau"]},{"name":"flowtypes.roblox","className":"ModuleScript","filePaths":["node_modules/@rbxts\\shared-internal\\src\\flowtypes.roblox.luau"]},{"name":"formatProdErrorMessage","className":"ModuleScript","filePaths":["node_modules/@rbxts\\shared-internal\\src\\formatProdErrorMessage.luau"]},{"name":"getComponentName","className":"ModuleScript","filePaths":["node_modules/@rbxts\\shared-internal\\src\\getComponentName.luau"]},{"name":"invariant","className":"ModuleScript","filePaths":["node_modules/@rbxts\\shared-internal\\src\\invariant.luau"]},{"name":"invokeGuardedCallbackImpl","className":"ModuleScript","filePaths":["node_modules/@rbxts\\shared-internal\\src\\invokeGuardedCallbackImpl.luau"]},{"name":"isValidElementType","className":"ModuleScript","filePaths":["node_modules/@rbxts\\shared-internal\\src\\isValidElementType.luau"]},{"name":"objectIs","className":"ModuleScript","filePaths":["node_modules/@rbxts\\shared-internal\\src\\objectIs.luau"]},{"name":"shallowEqual","className":"ModuleScript","filePaths":["node_modules/@rbxts\\shared-internal\\src\\shallowEqual.luau"]}]},{"name":"t","className":"Folder","children":[{"name":"lib","className":"Folder","children":[{"name":"ts","className":"ModuleScript","filePaths":["node_modules/@rbxts\\t\\lib\\ts.lua"]}]}]},{"name":"types","className":"Folder","children":[{"name":"include","className":"Folder","children":[{"name":"generated","className":"Folder"}]}]}]}]}]}]}